<ComponentRef Id="lapi.h"/>
<ComponentRef Id="lauxlib.h"/>
<ComponentRef Id="lcode.h"/>
<ComponentRef Id="lctype.h"/>
<ComponentRef Id="ldebug.h"/>
<ComponentRef Id="ldo.h"/>
<ComponentRef Id="lfunc.h"/>
<ComponentRef Id="lgc.h"/>
<ComponentRef Id="llex.h"/>
<ComponentRef Id="llimits.h"/>
<ComponentRef Id="lmem.h"/>
<ComponentRef Id="lobject.h"/>
<ComponentRef Id="lopcodes.h"/>
<ComponentRef Id="lparser.h"/>
<ComponentRef Id="lprefix.h"/>
<ComponentRef Id="lstate.h"/>
<ComponentRef Id="lstring.h"/>
<ComponentRef Id="ltable.h"/>
<ComponentRef Id="ltm.h"/>
<ComponentRef Id="lua.h"/>
<ComponentRef Id="luaconf.h"/>
<ComponentRef Id="lualib.h"/>
<ComponentRef Id="lundump.h"/>
<ComponentRef Id="lvm.h"/>
<ComponentRef Id="lzio.h"/>
